flask_ultrajson.py
setup.py
Flask_UltraJSON.egg-info/PKG-INFO
Flask_UltraJSON.egg-info/SOURCES.txt
Flask_UltraJSON.egg-info/dependency_links.txt
Flask_UltraJSON.egg-info/not-zip-safe
Flask_UltraJSON.egg-info/requires.txt
Flask_UltraJSON.egg-info/top_level.txt