Metadata-Version: 1.1
Name: Flask-UltraJSON
Version: 0.0.1
Summary: Intergrates UltraJSON with your Flask application.
Home-page: https://github.com/sunghyunzz/flask-ultrajson
Author: sunghyunzz
Author-email: me@sunghyunzz.com
License: MIT
Platform: any
Classifier: Development Status :: 3 - Alpha
Classifier: Environment :: Web Environment
Classifier: Intended Audience :: Developers
Classifier: License :: OSI Approved :: MIT License
Classifier: Programming Language :: Python :: 2
Classifier: Programming Language :: Python :: 2.6
Classifier: Programming Language :: Python :: 2.7
Classifier: Programming Language :: Python :: 3
Classifier: Programming Language :: Python :: 3.3
Classifier: Programming Language :: Python :: 3.4
Classifier: Programming Language :: Python :: 3.5
